cacao_accounting_desktop/__init__.py
cacao_accounting_desktop/__main.py
cacao_accounting_desktop/assets/CacaoAccounting.bmp
cacao_accounting_desktop/assets/CacaoAccounting.png
cacao_accounting_desktop/assets/CacaoAccountingRotate.bmp
cacao_accounting_desktop/assets/arrow-counterclockwise.png
cacao_accounting_desktop/assets/bmosoluciones.png
cacao_accounting_desktop/assets/play-fill.png
cacao_accounting_desktop/assets/plus-circle.png
cacao_accounting_desktop/assets/sliders.png
cacao_accounting_desktop-2025.4.7.dist-info/LICENSE
cacao_accounting_desktop-2025.4.7.dist-info/METADATA
cacao_accounting_desktop-2025.4.7.dist-info/WHEEL
cacao_accounting_desktop-2025.4.7.dist-info/entry_points.txt
cacao_accounting_desktop-2025.4.7.dist-info/top_level.txt
cacao_accounting_desktop-2025.4.7.dist-info/RECORD
