Metadata-Version: 2.1
Name: cacao-accounting-desktop
Version: 2025.4.7
Summary: Cacao Accounting Desktop App.
Author: William Moreno Reyes
Author-email: BMO Soluciones <development@bmogroup.solutions>
Classifier: License :: OSI Approved :: Apache Software License
Classifier: Natural Language :: Spanish
Classifier: Operating System :: OS Independent
Classifier: Programming Language :: Python :: 3 :: Only
Classifier: Programming Language :: Python :: 3.8
Classifier: Programming Language :: Python :: 3.9
Classifier: Programming Language :: Python :: 3.10
Classifier: Programming Language :: Python :: 3.11
Classifier: Programming Language :: Python :: 3.12
Classifier: Programming Language :: Python :: Implementation :: CPython
Requires-Python: >=3.8
License-File: LICENSE
Requires-Dist: appdirs
Requires-Dist: cacao-accounting
Requires-Dist: customtkinter
Requires-Dist: CTkMessagebox
Requires-Dist: flaskwebgui
Requires-Dist: pillow
